Pylette/__init__.py
Pylette/auxiliary.py
Pylette/cmd.py
Pylette/color.py
Pylette/color_extraction.py
Pylette/gui.py
Pylette/palette.py
pylette_windows-3.0.0.dist-info/LICENSE.md
pylette_windows-3.0.0.dist-info/METADATA
pylette_windows-3.0.0.dist-info/WHEEL
pylette_windows-3.0.0.dist-info/entry_points.txt
pylette_windows-3.0.0.dist-info/top_level.txt
pylette_windows-3.0.0.dist-info/RECORD
