Metadata-Version: 2.1
Name: pylette-windows
Version: 3.0.0
Summary: Pylette for Windows
Author-email: Austin Bryant <c00481025@louisiana.edu>
License: MIT License
Project-URL: Homepage, https://github.com/IntoThatGoodNight/Pylette-Windows-Fork
Keywords: palette,color,image
Classifier: License :: OSI Approved :: MIT License
Classifier: Programming Language :: Python
Classifier: Programming Language :: Python :: 3
Requires-Python: >=3.11.4
License-File: LICENSE.md
Requires-Dist: numpy (==1.24.3)
Requires-Dist: Pillow (>=10.0.0)
Requires-Dist: PyQt5 (>=5.15.9)
Requires-Dist: scikit-learn (>=1.3.0)
